Metadata-Version: 2.1
Name: scrapy-tor-proxy-rotator
Version: 0.0.2
Summary: Rotate TOR IPs with Scrapy (forked from scrapy-tor-proxy-rotation 0.0.1)
Home-page: https://github.com/dragospopa420/scrapy-tor-proxy-rotation
Author: Dragos Popa 
Author-email: dragospopa420@gmail.com
Classifier: Programming Language :: Python :: 3
Classifier: License :: OSI Approved :: MIT License
Classifier: Operating System :: Unix
Requires-Python: >=3.6
License-File: LICENSE
